conftest.py
frequenz/api/microgrid/__init__.py
frequenz/api/microgrid/py.typed
frequenz/api/microgrid/v1/__init__.py
frequenz/api/microgrid/v1/microgrid_pb2.py
frequenz/api/microgrid/v1/microgrid_pb2.pyi
frequenz/api/microgrid/v1/microgrid_pb2_grpc.py
frequenz/api/microgrid/v1/microgrid_pb2_grpc.pyi
frequenz_api_microgrid-0.17.2.dist-info/LICENSE
frequenz_api_microgrid-0.17.2.dist-info/METADATA
frequenz_api_microgrid-0.17.2.dist-info/WHEEL
frequenz_api_microgrid-0.17.2.dist-info/top_level.txt
frequenz_api_microgrid-0.17.2.dist-info/RECORD
