Metadata-Version: 2.1
Name: frequenz-api-microgrid
Version: 0.17.2
Summary: Frequenz gRPC API for monitoring and control of microgrids
Author-email: Frequenz Energy-as-a-Service GmbH <floss@frequenz.com>
License: MIT
Project-URL: Changelog, https://github.com/frequenz-floss/frequenz-api-microgrid/releases
Project-URL: Issues, https://github.com/frequenz-floss/frequenz-api-microgrid/issues
Project-URL: Repository, https://github.com/frequenz-floss/frequenz-api-microgrid
Project-URL: Support, https://github.com/frequenz-floss/frequenz-api-microgrid/discussions/categories/support
Keywords: frequenz,python,api,grpc,protobuf,rpc,microgrid
Classifier: Development Status :: 3 - Alpha
Classifier: Intended Audience :: Developers
Classifier: License :: OSI Approved :: MIT License
Classifier: Programming Language :: Python :: 3
Classifier: Programming Language :: Python :: 3 :: Only
Classifier: Topic :: Software Development :: Libraries
Classifier: Typing :: Typed
Requires-Python: <4,>=3.11
License-File: LICENSE
Requires-Dist: frequenz-api-common<0.7,>=0.6.5
Requires-Dist: googleapis-common-protos<2,>=1.70.0
Requires-Dist: protobuf<8,>=6.31.1
Requires-Dist: grpcio<2,>=1.72.1
Provides-Extra: dev
Requires-Dist: frequenz-api-microgrid[dev-flake8,dev-formatting,dev-mkdocs,dev-mypy,dev-noxfile,dev-pylint,dev-pytest]; extra == "dev"
Provides-Extra: dev-flake8
Requires-Dist: flake8==7.0.0; extra == "dev-flake8"
Requires-Dist: flake8-docstrings==1.7.0; extra == "dev-flake8"
Requires-Dist: flake8-pyproject==1.2.3; extra == "dev-flake8"
Requires-Dist: pydoclint==0.4.1; extra == "dev-flake8"
Requires-Dist: pydocstyle==6.3.0; extra == "dev-flake8"
Provides-Extra: dev-formatting
Requires-Dist: black==24.4.2; extra == "dev-formatting"
Requires-Dist: isort==5.13.2; extra == "dev-formatting"
Provides-Extra: dev-mkdocs
Requires-Dist: mike==1.1.2; extra == "dev-mkdocs"
Requires-Dist: mkdocs-gen-files==0.5.0; extra == "dev-mkdocs"
Requires-Dist: mkdocs-literate-nav==0.6.1; extra == "dev-mkdocs"
Requires-Dist: mkdocs-material==9.5.20; extra == "dev-mkdocs"
Requires-Dist: mkdocstrings[python]==0.26.1; extra == "dev-mkdocs"
Requires-Dist: mkdocstrings-python==1.11.1; extra == "dev-mkdocs"
Requires-Dist: frequenz-repo-config[api]==0.9.1; extra == "dev-mkdocs"
Provides-Extra: dev-mypy
Requires-Dist: mypy==1.10.0; extra == "dev-mypy"
Requires-Dist: grpc-stubs==1.53.0.5; extra == "dev-mypy"
Requires-Dist: frequenz-api-microgrid[dev-mkdocs,dev-noxfile,dev-pytest]; extra == "dev-mypy"
Provides-Extra: dev-noxfile
Requires-Dist: nox==2024.4.15; extra == "dev-noxfile"
Requires-Dist: frequenz-repo-config[api]==0.9.1; extra == "dev-noxfile"
Provides-Extra: dev-pylint
Requires-Dist: pylint==3.1.0; extra == "dev-pylint"
Requires-Dist: frequenz-api-microgrid[dev-mkdocs,dev-noxfile,dev-pytest]; extra == "dev-pylint"
Provides-Extra: dev-pytest
Requires-Dist: pytest==8.2.0; extra == "dev-pytest"
Requires-Dist: frequenz-repo-config[extra-lint-examples]==0.9.1; extra == "dev-pytest"
